skrab/__init__.py
skrab/boliga.py
skrab/cli.py
skrab-0.1.0.dist-info/METADATA
skrab-0.1.0.dist-info/WHEEL
skrab-0.1.0.dist-info/entry_points.txt
skrab-0.1.0.dist-info/RECORD
