Metadata-Version: 2.1
Name: skrab
Version: 0.1.0
Summary: 
Author: Kasper Junge
Author-email: kasperjuunge@gmail.com
Requires-Python: >=3.12,<4.0
Classifier: Programming Language :: Python :: 3
Classifier: Programming Language :: Python :: 3.12
Classifier: Programming Language :: Python :: 3.13
Requires-Dist: aiohttp (>=3.10.10,<4.0.0)
Requires-Dist: pandas (>=2.2.3,<3.0.0)
Requires-Dist: requests (>=2.32.3,<3.0.0)
Requires-Dist: tqdm (>=4.66.6,<5.0.0)
Requires-Dist: typer (>=0.12.5,<0.13.0)
